mlrd/__init__.py
mlrd/__main__.py
mlrd/mlrd.py
mlrd-0.1.4.dist-info/entry_points.txt
mlrd-0.1.4.dist-info/LICENSE
mlrd-0.1.4.dist-info/WHEEL
mlrd-0.1.4.dist-info/METADATA
mlrd-0.1.4.dist-info/RECORD
