Metadata-Version: 2.1
Name: mlrd
Version: 0.1.4
Summary: Mcgrill Lecture Recording Download (mlrd) tool
Home-page: https://github.com/brendan-kellam/mlrd
License: MIT
Author: Brendan
Author-email: bshizzle1234@gmail.com
Requires-Python: >=3.8,<4.0
Classifier: License :: OSI Approved :: MIT License
Classifier: Programming Language :: Python :: 3
Classifier: Programming Language :: Python :: 3.8
Classifier: Programming Language :: Python :: 3.9
Requires-Dist: requests (>=2.25.0,<3.0.0)
Project-URL: Repository, https://github.com/brendan-kellam/mlrd
